{
  "1.1.0": {
    "revapi": {
      "ignore": [
        {
          "code": "java.annotation.added",
          "old": "@interface org.linkki.core.ui.aspects.annotation.BindStyleNames",
          "new": "@interface org.linkki.core.ui.aspects.annotation.BindStyleNames",
          "annotationType": "org.linkki.core.binding.descriptor.aspect.annotation.InheritedAspect",
          "justification": "LIN-1574"
        },
        {
          "code": "java.annotation.attributeValueChanged",
          "old": "@interface org.linkki.core.ui.aspects.annotation.BindStyleNames",
          "new": "@interface org.linkki.core.ui.aspects.annotation.BindStyleNames",
          "annotationType": "java.lang.annotation.Target",
          "attribute": "value",
          "oldValue": "{java.lang.annotation.ElementType.FIELD, java.lang.annotation.ElementType.METHOD}",
          "newValue": "{java.lang.annotation.ElementType.TYPE, java.lang.annotation.ElementType.FIELD, java.lang.annotation.ElementType.METHOD}",
          "justification": "FCOM-153"
        },
        {
          "code": "java.method.removed",
          "old": "method boolean org.linkki.core.vaadin.component.section.AbstractSection::isEditButtonAvailable()",
          "justification": "LIN-434 :: Method was unused and did not work properly for some cases"
        },
        {
          "code": "java.method.removed",
          "old": "method java.util.List<org.linkki.core.binding.descriptor.aspect.LinkkiAspectDefinition> org.linkki.core.defaults.columnbased.ColumnBasedComponentCreator::getContainerAspects()",
          "justification": "LIN-1574 :: Method was intended for internal usage"
        },
        {
          "code": "java.annotation.added",
          "old": "interface org.linkki.core.defaults.columnbased.pmo.ContainerPmo<ROW extends java.lang.Object>",
          "new": "interface org.linkki.core.defaults.columnbased.pmo.ContainerPmo<ROW extends java.lang.Object>",
          "justification": "LIN-1574 :: Use aspect annotations for table aspects"
        },
        {
          "regex": true,
          "code": "java.annotation.added",
          "old": "parameter .*",
          "new": "parameter .*",
          "annotationType": "edu\\.umd\\.cs\\.findbugs\\.annotations\\.CheckForNull",
          "justification": "@CheckForNull for parameters is compatible"
        },
        {
          "regex": true,
          "code": "java.method.defaultValueChanged",
          "justification": "LIN7",
          "oldValue": "\"\"",
          "newValue": "\"derived\\.by\\.linkki\"",
          "methodName": "caption"
        },
        {
          "regex": true,
          "code": "java.method.defaultValueChanged",
          "justification": "LIN7",
          "oldValue": "\"\"",
          "newValue": "\"derived\\.by\\.linkki\"",
          "methodName": "label"
        },
        {
          "code": "java.class.defaultSerializationChanged",
          "old": "class com.vaadin.navigator.Navigator",
          "new": "class com.vaadin.navigator.Navigator",
          "justification": "LIN-1595 :: Update Vaadin version to 8.9.2"
        },
        {
          "code": "java.class.nonFinalClassInheritsFromNewClass",
          "old": "class org.linkki.core.ui.aspects.BindReadOnlyAspectDefinition",
          "new": "class org.linkki.core.ui.aspects.BindReadOnlyAspectDefinition",
          "justification": "LIN-1658 :: Make BindReadOnlyAspectDefinition extend ModelToUiAspectDefinition"
        }
      ]
    }
  },
  "1.2.0": {
    "revapi": {
      "ignore": [
		{
          "code": "java.class.externalClassExposedInAPI",
          "new": "enum org.linkki.core.defaults.ui.aspects.types.AlignmentType",
          "justification": "LIN-245"
        }
      ]
	}
  }
}
